fastapi_ccli-0.0.3.dist-info/METADATA
fastapi_ccli-0.0.3.dist-info/WHEEL
fastapi_ccli-0.0.3.dist-info/entry_points.txt
fastapi_ccli-0.0.3.dist-info/licenses/LICENSE
fastapi_ccli/__init__.py
fastapi_ccli/cloner/__init__.py
fastapi_ccli/cloner/cloner_en.py
fastapi_ccli/cloner/cloner_en_form.py
fastapi_ccli/main.py
fastapi_ccli/utils/__init__.py
fastapi_ccli/utils/get_country.py
fastapi_ccli/utils/get_ip.py
fastapi_ccli/utils/get_path.py
fastapi_ccli-0.0.3.dist-info/RECORD
